d10z/__init__.py
d10z/bigstart.py
d10z/constants.py
d10z/filaments.py
d10z/flower_of_life.py
d10z/fv_relation.py
d10z/galactic_rotation.py
d10z/gm1051.py
d10z/gravity.py
d10z/infifoton.py
d10z/isis_law.py
d10z/morphopy-cli.py
d10z/morphopy__data__samples__init__.py
d10z/morphopy__init__.py
d10z/morphopy_data__init__.py
d10z/morphopy_data_registry.py
d10z/morphopy_downloader.py
d10z/n_field.py
d10z/neuro.py
d10z/neusars.py
d10z/nodal_density.py
d10z/omdi.py
d10z/quickstart.py
d10z/sahana_law.py
d10z/tta.py
d10z/tta_simulator.py
d10z/universal_force.py
d10z/zn.py
d10z-2.0.2.dist-info/licenses/LICENSE
d10z-2.0.2.dist-info/METADATA
d10z-2.0.2.dist-info/WHEEL
d10z-2.0.2.dist-info/top_level.txt
d10z-2.0.2.dist-info/RECORD
