Metadata-Version: 2.4
Name: d10z
Version: 2.0.2
Summary: D10Z Framework - Manual de la Mecánica del Infinito (Big Start, TTA, Neusar, OmDi, Infifotón, Z, N, F=f·v(Zn), GM10⁻⁵¹, Ley Sahana, Ley Isis).
Home-page: https://github.com/jamilaltha/TTA-Universal-Data
Author: Jamil Al Thani
Author-email: Jamil Al Thani <jamil@d10z.org>
License: CHLL-D10Z-v1.1
Project-URL: Homepage, https://github.com/d10z-institute/d10z
Project-URL: Documentation, https://d10z.org
Project-URL: Source, https://github.com/d10z-institute/d10z
Project-URL: Issues, https://github.com/d10z-institute/d10z/issues
Keywords: physics,cosmology,fractal,D10Z,TTA,GM10-51
Platform: any
Requires-Python: >=3.6
License-File: LICENSE
Requires-Dist: numpy>=1.21
Requires-Dist: scipy>=1.7
Requires-Dist: morphopy>=0.7.5
Dynamic: author
Dynamic: home-page
Dynamic: license-file
Dynamic: requires-python
